grpc_opentracing/__init__.py
grpc_opentracing/_client.py
grpc_opentracing/_server.py
grpc_opentracing/_utilities.py
grpc_opentracing/grpcext/__init__.py
grpc_opentracing/grpcext/_interceptor.py
grpcio_opentracing-1.1.3.dist-info/METADATA
grpcio_opentracing-1.1.3.dist-info/RECORD
grpcio_opentracing-1.1.3.dist-info/WHEEL
grpcio_opentracing-1.1.3.dist-info/top_level.txt
