Metadata-Version: 2.1
Name: grpcio-opentracing
Version: 1.1.3
Summary: Python OpenTracing Extensions for gRPC
Home-page: UNKNOWN
Author: LightStep
Author-email: UNKNOWN
License: UNKNOWN
Keywords: opentracing
Platform: UNKNOWN
Classifier: Operating System :: OS Independent
Classifier: Programming Language :: Python :: 2.7
Classifier: Programming Language :: Python :: 3
Classifier: Programming Language :: Python :: 3.6
Requires-Dist: opentracing (>=1.2.2)
Requires-Dist: grpcio (>=1.1.3)
Requires-Dist: six (>=1.10)
